README.md
setup.py
src/ipython_kusto.egg-info/PKG-INFO
src/ipython_kusto.egg-info/SOURCES.txt
src/ipython_kusto.egg-info/dependency_links.txt
src/ipython_kusto.egg-info/not-zip-safe
src/ipython_kusto.egg-info/requires.txt
src/ipython_kusto.egg-info/top_level.txt
src/kusto/__init__.py
src/kusto/magic.py