Metadata-Version: 2.1
Name: ipython-kusto
Version: 0.0.8
Summary: Microsoft Kusto access via IPython
Home-page: https://github.com/gramster/ipython-kusto
Author: Graham Wheeler
Author-email: graham@grahamwheeler.com
License: MIT
Keywords: database ipython kusto
Platform: UNKNOWN
Classifier: Development Status :: 3 - Alpha
Classifier: Environment :: Console
Classifier: License :: OSI Approved :: MIT License
Classifier: Topic :: Database
Classifier: Topic :: Database :: Front-Ends
Classifier: Programming Language :: Python :: 3
